[
  {
    "number": "090000",
    "name": "Anoniem Persoon",
    "classNumber": "1",
    "interest": ""
  },
  {
    "number": "090001",
    "name": "Anoniem Persoon",
    "classNumber": "1",
    "interest": ""
  },
  {
    "number": "090002",
    "name": "Anoniem Persoon",
    "classNumber": "1",
    "interest": ""
  },
  {
    "number": "090003",
    "name": "Anoniem Persoon",
    "classNumber": "1",
    "interest": ""
  },
  {
    "number": "090004",
    "name": "Anoniem Persoon",
    "classNumber": "1",
    "interest": ""
  },
  {
    "number": "090005",
    "name": "Anoniem Persoon",
    "classNumber": "1",
    "interest": ""
  },
  {
    "number": "090006",
    "name": "Anoniem Persoon",
    "classNumber": "1",
    "interest": ""
  },
  {
    "number": "090007",
    "name": "Anoniem Persoon",
    "classNumber": "1",
    "interest": ""
  },
  {
    "number": "090008",
    "name": "Anoniem Persoon",
    "classNumber": "1",
    "interest": ""
  }
]




